[
  {
    "showChapter": true,
    "headerText": "1. Скоростной режим",
    "chapter": [
      {
        "text": "1.1 Нарушение скоростного режима (8.000)",
        "penalty": 8000,
        "code": "1.1 КоАП"
      },
      {
        "text": "1.2 Нарушение скор. режима + ДТП (15.000 + лишение)",
        "penalty": 15000,
        "code": "1.2 КоАП"
      }
    ]
  },
  {
    "showChapter": true,
    "headerText": "2. Дорожное движение",
    "chapter": [
      {
        "text": "2.1 Езда по встречной полосе (15.000 + лишение)",
        "penalty": 15000,
        "code": "2.1 КоАП"
      },
      {
        "text": "2.2 Встречка + ДТП (20.000 + лишение)",
        "penalty": 20000,
        "code": "2.2 КоАП"
      },
      {
        "text": "2.3 Пересечение сплошной линии (15.000)",
        "penalty": 15000,
        "code": "2.3 КоАП"
      },
      {
        "text": "2.4 Бег по дороге (2.000)",
        "penalty": 2000,
        "code": "2.4 КоАП"
      },
      {
        "text": "2.5 Проезд знака Стоп без остановки (5.000)",
        "penalty": 5000,
        "code": "2.5 КоАП"
      }
    ]
  },
  {
    "showChapter": true,
    "headerText": "3. Светофор",
    "chapter": [
      {
        "text": "3.1 Проезд на красный сигнал (5.000)",
        "penalty": 5000,
        "code": "3.1 КоАП"
      },
      {
        "text": "3.2 Проезд на красный + ДТП (15.000 + лишение)",
        "penalty": 15000,
        "code": "3.2 КоАП"
      }
    ]
  },
  {
    "showChapter": true,
    "headerText": "4. Парковка",
    "chapter": [
      {
        "text": "4.1 Парковка в неположенном месте (15.000)",
        "penalty": 15000,
        "code": "4.1 КоАП"
      }
    ]
  },
  {
    "showChapter": true,
    "headerText": "5. Движение в неположенном месте / Телефон",
    "chapter": [
      {
        "text": "5.1 Движение по тротуару/газону (10.000)",
        "penalty": 10000,
        "code": "5.1 КоАП"
      },
      {
        "text": "5.2 Разговор по телефону во время движения (4.000)",
        "penalty": 4000,
        "code": "5.2 КоАП"
      }
    ]
  },
  {
    "showChapter": true,
    "headerText": "6. Игнорирование сирен спец. служб",
    "chapter": [
      {
        "text": "6.1 Игнорирование сирен (5.000)",
        "penalty": 5000,
        "code": "6.1 КоАП"
      },
      {
        "text": "6.2 Игнорирование сирен + ДТП (10.000 + лишение)",
        "penalty": 10000,
        "code": "6.2 КоАП"
      }
    ]
  },
  {
    "showChapter": true,
    "headerText": "7. Затруднение движения / Неисправность",
    "chapter": [
      {
        "text": "7.1 Затруднение движения ТС (5.000)",
        "penalty": 5000,
        "code": "7.1 КоАП"
      },
      {
        "text": "7.2 Езда на неисправном ТС (8.000)",
        "penalty": 8000,
        "code": "7.2 КоАП"
      }
    ]
  },
  {
    "showChapter": true,
    "headerText": "8. Рег. знак, Ремни, Шлем, Фары",
    "chapter": [
      {
        "text": "8.1 Передвижение без рег. знака (10.000)",
        "penalty": 10000,
        "code": "8.1 КоАП"
      },
      {
        "text": "8.2 Не пристегнутый ремень безопасности (2.000)",
        "penalty": 2000,
        "code": "8.2 КоАП"
      },
      {
        "text": "8.3 Езда без шлема (2.000)",
        "penalty": 2000,
        "code": "8.3 КоАП"
      },
      {
        "text": "8.4 Езда с выключенными фарами (5.000)",
        "penalty": 5000,
        "code": "8.4 КоАП"
      }
    ]
  },
  {
    "showChapter": true,
    "headerText": "9. Агрессивное вождение",
    "chapter": [
      {
        "text": "9.1 Агрессивное поведение на дороге (10.000 + лишение)",
        "penalty": 10000,
        "code": "9.1 КоАП"
      }
    ]
  },
  {
    "showChapter": true,
    "headerText": "10. Тонировка",
    "chapter": [
      {
        "text": "10.1 Тонировка лобового < 75% (7.000)",
        "penalty": 7000,
        "code": "10.1 КоАП"
      },
      {
        "text": "10.2 Тонировка боковых < 70% (7.000)",
        "penalty": 7000,
        "code": "10.2 КоАП"
      }
    ]
  },
  {
    "showChapter": true,
    "headerText": "11. Шины",
    "chapter": [
      {
        "text": "11.1 Летние шины в зимний период (5.000)",
        "penalty": 5000,
        "code": "11.1 КоАП"
      }
    ]
  },
  {
    "showChapter": true,
    "headerText": "13. Нецензурная лексика, оскорбление",
    "chapter": [
      {
        "text": "13.1 Использование ненормативной лексики (3.000)",
        "penalty": 3000,
        "code": "13.1 КоАП"
      },
      {
        "text": "13.2 Оскорбление граждан (15.000)",
        "penalty": 15000,
        "code": "13.2 КоАП"
      },
      {
        "text": "13.3 Оскорбление сотрудника МВД (20.000)",
        "penalty": 20000,
        "code": "13.3 КоАП"
      }
    ]
  },
  {
    "showChapter": true,
    "headerText": "14-15. Алкоголь, курение",
    "chapter": [
      {
        "text": "14.1 Курение в общественных местах (3.000)",
        "penalty": 3000,
        "code": "14.1 КоАП"
      },
      {
        "text": "14.2 Распитие спиртного в общ. местах (3.000)",
        "penalty": 3000,
        "code": "14.2 КоАП"
      },
      {
        "text": "15.1 Заведомо ложный вызов (10.000)",
        "penalty": 10000,
        "code": "15.1 КоАП"
      }
    ]
  }
]